{
"speed": 0.1,
"parkRightInFrontOfTheEntrancePrice": 300,
"freeBottleOfWaterPrice": 100,
"prices":
[
{"name": "(E)conomy", "price": 1000},
{"name": "(C)omfort", "price": 1500},
{"name": "Comfort(+)", "price": 1700},
{"name": "(B)usiness", "price": 4000}
],
"cities": {"Visitacion Valley":{"latitude":37.71715,"longitude":-122.40433},"Noe Valley":{"latitude":37.75018,"longitude":-122.43369},"Spring Valley Lake":{"latitude":34.49364,"longitude":-117.26832},"Silver Lakes":{"latitude":34.74558,"longitude":-117.34098},"Silver Lake":{"latitude":34.08668,"longitude":-118.27023},"Phoenix Lake":{"latitude":38.00594,"longitude":-120.30702},"Echo Park":{"latitude":34.07808,"longitude":-118.26066},"Buckhorn":{"latitude":38.45216,"longitude":-120.52854},"Sun Village":{"latitude":34.55952,"longitude":-117.95676},"Rio Vista":{"latitude":38.16389,"longitude":-121.69583},"Matheny":{"latitude":36.17066,"longitude":-119.35158},"Patterson Tract":{"latitude":36.37952,"longitude":-119.2956},"Teviston":{"latitude":35.92894,"longitude":-119.27831},"West Hills":{"latitude":34.19731,"longitude":-118.64398},"Contra Costa Centre":{"latitude":37.92752,"longitude":-122.05786},"Eastvale":{"latitude":33.96358,"longitude":-117.56418},"Old Fig Garden":{"latitude":36.79885,"longitude":-119.80515},"Red Corral":{"latitude":38.41165,"longitude":-120.60552},"Poplar-Cotton Center":{"latitude":36.05635,"longitude":-119.14919},"Oroville East":{"latitude":39.51126,"longitude":-121.47519},"Vandenberg Air Force Base":{"latitude":34.7483,"longitude":-120.51817},"Dixon Lane-Meadow Creek":{"latitude":37.38639,"longitude":-118.41527},"North Lakeport":{"latitude":39.08831,"longitude":-122.90538},"Westhaven-Moonstone":{"latitude":41.04489,"longitude":-124.10239},"View Park-Windsor Hills":{"latitude":33.99551,"longitude":-118.34835},"West Whittier-Los Nietos":{"latitude":33.976,"longitude":-118.06909},"Vincent":{"latitude":34.50055,"longitude":-118.11646},"West Modesto":{"latitude":37.61754,"longitude":-121.03914},"Acalanes Ridge":{"latitude":37.90472,"longitude":-122.07857},"Taft Mosswood":{"latitude":37.91385,"longitude":-121.28316},"Yosemite Valley":{"latitude":37.74075,"longitude":-119.57788},"Tamalpais-Homestead Valley":{"latitude":37.87834,"longitude":-122.53625},"Sunnyside-Tahoe City":{"latitude":39.15023,"longitude":-120.1612},"Monument Hills":{"latitude":38.66429,"longitude":-121.87566},"Meadowbrook":{"latitude":33.72578,"longitude":-117.28509},"Fruitridge Pocket":{"latitude":38.53265,"longitude":-121.45581},"Bret Harte":{"latitude":37.60207,"longitude":-121.00519},"Camp Pendleton North":{"latitude":33.31465,"longitude":-117.31603},"Edwards Air Force Base":{"latitude":34.91637,"longitude":-117.93535},"Lucas Valley-Marinwood":{"latitude":38.04011,"longitude":-122.5755},"Casa de Oro-Mount Helix":{"latitude":32.76397,"longitude":-116.96877},"Camp Pendleton South":{"latitude":33.22844,"longitude":-117.37929},"Challenge-Brownsville":{"latitude":39.46447,"longitude":-121.26338},"Florence-Graham":{"latitude":33.96772,"longitude":-118.24438},"Highlands-Baywood Park":{"latitude":37.52272,"longitude":-122.34506},"Hilmar-Irwin":{"latitude":37.40454,"longitude":-120.85042},"March Air Force Base":{"latitude":33.89209,"longitude":-117.2631},"Fetters Hot Springs-Agua Caliente":{"latitude":38.3214,"longitude":-122.48682},"Lemoore Station":{"latitude":36.26326,"longitude":-119.90476},"Lagunitas-Forest Knolls":{"latitude":38.01793,"longitude":-122.69124},"Idyllwild-Pine Cove":{"latitude":33.74429,"longitude":-116.72587},"La Crescenta-Montrose":{"latitude":34.23216,"longitude":-118.23529},"Larkfield-Wikiup":{"latitude":38.51342,"longitude":-122.75094},"Bonadelle Ranchos-Madera Ranchos":{"latitude":36.98467,"longitude":-119.87463},"Black Point-Green Point":{"latitude":38.11547,"longitude":-122.51318},"Bertsch-Oceanview":{"latitude":41.7525,"longitude":-124.15875},"Westwood":{"latitude":34.05612,"longitude":-118.43063},"Bayview":{"latitude":40.77263,"longitude":-124.18395},"Willow Creek":{"latitude":40.93958,"longitude":-123.63144},"Rancho Tehama Reserve":{"latitude":40.01569,"longitude":-122.40072},"Yreka":{"latitude":41.73542,"longitude":-122.63447},"Stevenson Ranch":{"latitude":34.39048,"longitude":-118.57372},"Desert Edge":{"latitude":33.92417,"longitude":-116.44139},"Beale Air Force Base":{"latitude":39.10917,"longitude":-121.35444},"Vineyard":{"latitude":38.46449,"longitude":-121.34692},"Arden-Arcade":{"latitude":38.6025,"longitude":-121.37854},"Aptos Hills-Larkin Valley":{"latitude":36.96064,"longitude":-121.83404},"Rio Dell":{"latitude":40.4993,"longitude":-124.10644},"Shasta Lake":{"latitude":40.68043,"longitude":-122.37084},"Shasta":{"latitude":40.59932,"longitude":-122.49196},"Redding":{"latitude":40.58654,"longitude":-122.39168},"Redway":{"latitude":40.12014,"longitude":-123.82336},"Weaverville":{"latitude":40.73098,"longitude":-122.94197},"Susanville":{"latitude":40.41628,"longitude":-120.65301},"Weed":{"latitude":41.42265,"longitude":-122.38613},"Shingletown":{"latitude":40.49238,"longitude":-121.88916},"Happy Camp":{"latitude":41.79275,"longitude":-123.3808},"Gerber":{"latitude":40.05627,"longitude":-122.15027},"Greenville":{"latitude":40.13961,"longitude":-120.95107},"Fortuna":{"latitude":40.59819,"longitude":-124.15728},"Janesville":{"latitude":40.29656,"longitude":-120.52411},"Hydesville":{"latitude":40.54763,"longitude":-124.09727},"Johnstonville":{"latitude":40.38434,"longitude":-120.58745},"Humboldt Hill":{"latitude":40.72596,"longitude":-124.18978},"Hayfork":{"latitude":40.55431,"longitude":-123.18308},"McKinleyville":{"latitude":40.94652,"longitude":-124.10062},"Lewiston":{"latitude":40.70737,"longitude":-122.80752},"Los Molinos":{"latitude":40.02127,"longitude":-122.10027},"McCloud":{"latitude":41.25571,"longitude":-122.13945},"Montague":{"latitude":41.7282,"longitude":-122.5278},"Pine Hills":{"latitude":40.73318,"longitude":-124.15228},"Red Bluff":{"latitude":40.17849,"longitude":-122.23583},"Myrtletown":{"latitude":40.78874,"longitude":-124.13034},"Mount Shasta":{"latitude":41.31024,"longitude":-122.31225},"Palo Cedro":{"latitude":40.56376,"longitude":-122.23889},"Ferndale":{"latitude":40.57624,"longitude":-124.26394},"Anderson":{"latitude":40.44821,"longitude":-122.29778},"Bayside":{"latitude":40.84235,"longitude":-124.06367},"Arcata":{"latitude":40.86652,"longitude":-124.08284},"Chester":{"latitude":40.30627,"longitude":-121.23191},"Central Valley (historical)":{"latitude":40.68043,"longitude":-122.37112},"Blue Lake":{"latitude":40.88291,"longitude":-123.98395},"Bella Vista":{"latitude":40.64071,"longitude":-122.2325},"Burney":{"latitude":40.88238,"longitude":-121.66082},"Cutten":{"latitude":40.76985,"longitude":-124.14284},"Cottonwood":{"latitude":40.38571,"longitude":-122.28084},"Eureka":{"latitude":40.80207,"longitude":-124.16367},"Crescent City":{"latitude":41.75595,"longitude":-124.20175},"Dunsmuir":{"latitude":41.20821,"longitude":-122.27195},"West Bishop":{"latitude":37.36104,"longitude":-118.45511},"Yucca Valley":{"latitude":34.11417,"longitude":-116.43224},"Three Rivers":{"latitude":36.43884,"longitude":-118.90454},"Wasco":{"latitude":35.59412,"longitude":-119.34095},"Sheridan":{"latitude":38.97962,"longitude":-121.37551},"Alturas":{"latitude":41.48714,"longitude":-120.54349},"Yucaipa":{"latitude":34.03363,"longitude":-117.04309},"Winter Gardens":{"latitude":32.83116,"longitude":-116.93336},"Winters":{"latitude":38.52491,"longitude":-121.9708},"Winton":{"latitude":37.38938,"longitude":-120.61325},"Windsor":{"latitude":38.54713,"longitude":-122.81638},"Winchester":{"latitude":33.70697,"longitude":-117.08447},"Woodlake":{"latitude":36.41356,"longitude":-119.09872},"Woodbridge":{"latitude":38.15408,"longitude":-121.30134},"Woodacre":{"latitude":38.0127,"longitude":-122.64526},"Wofford Heights":{"latitude":35.7069,"longitude":-118.4562},"Woodcrest":{"latitude":33.88224,"longitude":-117.35727},"Yountville":{"latitude":38.40158,"longitude":-122.36081},"Woodland Hills":{"latitude":34.16834,"longitude":-118.60592},"Wrightwood":{"latitude":34.36083,"longitude":-117.63339},"Woodside":{"latitude":37.42994,"longitude":-122.25386},"Woodland":{"latitude":38.67852,"longitude":-121.7733},"Yosemite Lakes":{"latitude":37.19106,"longitude":-119.77265},"Yuba City":{"latitude":39.14045,"longitude":-121.61691},"Yorba Linda":{"latitude":33.88863,"longitude":-117.81311},"Woodville":{"latitude":36.09356,"longitude":-119.199},"Wilton":{"latitude":38.41186,"longitude":-121.27217},"West Hollywood":{"latitude":34.09001,"longitude":-118.36174},"West Rancho Dominguez":{"latitude":33.8939,"longitude":-118.27063},"West Park":{"latitude":36.71023,"longitude":-119.85126},"West Menlo Park":{"latitude":37.43355,"longitude":-122.20302},"West Covina":{"latitude":34.06862,"longitude":-117.93895},"West Puente Valley":{"latitude":34.05168,"longitude":-117.9684},"Westlake Village":{"latitude":34.14584,"longitude":-118.80565},"West Sacramento":{"latitude":38.58046,"longitude":-121.53023},"Westminster":{"latitude":33.75918,"longitude":-118.00673},"Westmont":{"latitude":33.9414,"longitude":-118.3023},"Wheatland":{"latitude":39.00989,"longitude":-121.42301},"Westmorland":{"latitude":33.03727,"longitude":-115.62138},"Whittier":{"latitude":33.97918,"longitude":-118.03284},"Wildomar":{"latitude":33.59891,"longitude":-117.28004},"Willows":{"latitude":39.52433,"longitude":-122.19359},"Willowbrook":{"latitude":33.91696,"longitude":-118.25507},"Williams":{"latitude":39.15461,"longitude":-122.14942},"Willits":{"latitude":39.40961,"longitude":-123.35557},"Ventura":{"latitude":34.27834,"longitude":-119.29317},"Villa Park":{"latitude":33.81446,"longitude":-117.81311},"Venice":{"latitude":33.99084,"longitude":-118.46008},"Vandenberg Village":{"latitude":34.70832,"longitude":-120.46766},"Victorville":{"latitude":34.53611,"longitude":-117.29116},"Vista":{"latitude":33.20004,"longitude":-117.24254},"Vista Santa Rosa":{"latitude":33.6278,"longitude":-116.21806},"Waldon":{"latitude":37.92631,"longitude":-122.05552},"Visalia":{"latitude":36.33023,"longitude":-119.29206},"Walnut":{"latitude":34.02029,"longitude":-117.86534},"Waterford":{"latitude":37.64132,"longitude":-120.76048},"Walnut Creek":{"latitude":37.90631,"longitude":-122.06496},"Walnut Park":{"latitude":33.96807,"longitude":-118.22507},"Walnut Grove":{"latitude":38.24214,"longitude":-121.51162},"Weldon":{"latitude":35.66579,"longitude":-118.29036},"West Carson":{"latitude":33.82168,"longitude":-118.29257},"West Athens":{"latitude":33.92335,"longitude":-118.30341},"Watsonville":{"latitude":36.91023,"longitude":-121.75689},"Weedpatch":{"latitude":35.23802,"longitude":-118.9151},"North Tustin":{"latitude":33.76446,"longitude":-117.79394},"Twentynine Palms":{"latitude":34.13556,"longitude":-116.05417},"Turlock":{"latitude":37.49466,"longitude":-120.84659},"Twain Harte":{"latitude":38.03965,"longitude":-120.23269},"Tustin":{"latitude":33.74585,"longitude":-117.82617},"Ukiah":{"latitude":39.15017,"longitude":-123.20778},"Upland":{"latitude":34.09751,"longitude":-117.64839},"Twin Lakes":{"latitude":36.96745,"longitude":-121.99802},"Universal City":{"latitude":34.1389,"longitude":-118.35341},"Union City":{"latitude":37.59577,"longitude":-122.01913},"Vacaville":{"latitude":38.35658,"longitude":-121.98774},"Val Verde":{"latitude":34.445,"longitude":-118.65759},"Upper Lake":{"latitude":39.16461,"longitude":-122.91055},"Valinda":{"latitude":34.04529,"longitude":-117.94367},"Valencia":{"latitude":34.44361,"longitude":-118.60953},"Valley Center":{"latitude":33.21837,"longitude":-117.0342},"Valley Springs":{"latitude":38.19159,"longitude":-120.8291},"Van Nuys":{"latitude":34.18667,"longitude":-118.44897},"Valle Vista":{"latitude":33.7478,"longitude":-116.89336},"Vallejo":{"latitude":38.10409,"longitude":-122.25664},"Truckee":{"latitude":39.32796,"longitude":-120.18325},"Topanga":{"latitude":34.09362,"longitude":-118.60147},"Torrance":{"latitude":33.83585,"longitude":-118.34063},"Tipton":{"latitude":36.0594,"longitude":-119.31206}}
}